crawel_utils/__init__.py
crawel_utils/_version.py
crawel_utils/agency.py
crawel_utils/download.py
crawel_utils/name2id.py
db_utils/__init__.py
db_utils/handle.py
db_utils/mongoutil.py
simplecat-1.1.4.dist-info/DESCRIPTION.rst
simplecat-1.1.4.dist-info/METADATA
simplecat-1.1.4.dist-info/RECORD
simplecat-1.1.4.dist-info/WHEEL
simplecat-1.1.4.dist-info/metadata.json
simplecat-1.1.4.dist-info/top_level.txt
