Metadata-Version: 2.0
Name: simplecat
Version: 1.1.4
Summary: A python3 library for download Movie comment from Maoyan
Home-page: https://github.com/VIMerhan/MaoyanCrawel
Author: Acke
Author-email: vimer757216574@gmail.com
License: Apache
Platform: all
Requires-Dist: beautifulsoup4 (>=4.6.0builtwith>=1.3.3certifi>=2016.2.28requests>=2.14.2simplejson=>=3.11.1six=>=1.11.0threadpool=>=1.3.2lxml=>=4.2.4pymongo>=3.4.0tqdm>=4.15.0)
